odoo/addons/stock_picking_show_linked/README.rst
odoo/addons/stock_picking_show_linked/__init__.py
odoo/addons/stock_picking_show_linked/__manifest__.py
odoo/addons/stock_picking_show_linked/i18n/stock_picking_show_linked.pot
odoo/addons/stock_picking_show_linked/models/__init__.py
odoo/addons/stock_picking_show_linked/models/stock_picking.py
odoo/addons/stock_picking_show_linked/readme/CONTRIBUTORS.rst
odoo/addons/stock_picking_show_linked/readme/DESCRIPTION.rst
odoo/addons/stock_picking_show_linked/static/description/icon.png
odoo/addons/stock_picking_show_linked/static/description/index.html
odoo/addons/stock_picking_show_linked/views/stock_picking.xml
odoo13_addon_stock_picking_show_linked-13.0.1.0.2.dist-info/METADATA
odoo13_addon_stock_picking_show_linked-13.0.1.0.2.dist-info/WHEEL
odoo13_addon_stock_picking_show_linked-13.0.1.0.2.dist-info/top_level.txt
odoo13_addon_stock_picking_show_linked-13.0.1.0.2.dist-info/RECORD
